exping/__init__.py
exping/entry.py
exping/functions.py
exping-1.0.0.dist-info/METADATA
exping-1.0.0.dist-info/WHEEL
exping-1.0.0.dist-info/entry_points.txt
exping-1.0.0.dist-info/top_level.txt
exping-1.0.0.dist-info/RECORD
